gridmlip/__init__.py
gridmlip/_neighborhood.py
gridmlip/_percolation_analysis.py
gridmlip/cli.py
gridmlip/core.py
gridmlip/utils.py
gridmlip-0.1.1.dist-info/LICENSE
gridmlip-0.1.1.dist-info/METADATA
gridmlip-0.1.1.dist-info/WHEEL
gridmlip-0.1.1.dist-info/top_level.txt
gridmlip-0.1.1.dist-info/zip-safe
gridmlip-0.1.1.dist-info/RECORD
