Metadata-Version: 2.1
Name: gridmlip
Version: 0.1.1
Summary: Grid-based method for calculating the percolation barrier of mobile species using machine learning interatomic potentials
Home-page: https://github.com/dembart/gridmlip
Author: Artem Dembitskiy
Author-email: art.dembitskiy@gmail.com
License: MIT
Keywords: MLIP,percolation barrier
Platform: UNKNOWN
Classifier: Programming Language :: Python :: 3
Classifier: License :: OSI Approved :: MIT License
Classifier: Operating System :: OS Independent
License-File: LICENSE
Requires-Dist: pandas
Requires-Dist: numpy
Requires-Dist: scipy
Requires-Dist: ase
Requires-Dist: tqdm
Requires-Dist: joblib
